pypkgs_xy/__init__.py
pypkgs_xy/pypkgs_xy.py
pypkgs_xy-0.1.0.dist-info/LICENSE
pypkgs_xy-0.1.0.dist-info/WHEEL
pypkgs_xy-0.1.0.dist-info/METADATA
pypkgs_xy-0.1.0.dist-info/RECORD
