Metadata-Version: 2.1
Name: pypkgs-xy
Version: 0.1.0
Summary: toy Python package for DSCI 524 individual assignment 1 by Xudong Yang
License: MIT
Author: Xudong Yang
Author-email: xd1222@student.ubc.ca
Requires-Python: >=3.8,<4.0
Classifier: License :: OSI Approved :: MIT License
Classifier: Programming Language :: Python :: 3
Classifier: Programming Language :: Python :: 3.8
Classifier: Programming Language :: Python :: 3.9
Requires-Dist: pandas (>=1.2.2,<2.0.0)
